{
  "autenticar": [
    {
      "username": "teste",
      "password": "teste"
    }
  ],
  "modelos": [
    {
      "name": "texte modelo",
      "content": "modelando mesmo",
      "id": 3
    },
    {
      "name": "informal",
      "content": "precios que voce compareça a empresa",
      "id": 4
    }
  ],
  "canais": [
    {
      "name": "sms",
      "id": 5
    },
    {
      "name": "email",
      "id": 6
    }
  ],
  "mala-direta": [
    {
      "template_id": "text",
      "file": "C:\\fakepath\\semec.txt",
      "interested_unit": "",
      "id": 3
    },
    {
      "template_id": "texte modelo",
      "file": "C:\\fakepath\\semec.txt",
      "interested_unit": "",
      "id": 4
    },
    {
      "template_id": "texte modelo",
      "file": "C:\\fakepath\\semec.txt",
      "interested_unit": "",
      "id": 5
    },
    {
      "template_id": "texte modelo",
      "file": "C:\\fakepath\\semec.txt",
      "interested_unit": "",
      "id": 6
    }
  ],
  "status": [
    {
      "name": "enviado",
      "id": 1
    }
  ]
}